krxpy/__init__.py
krxpy/calender/__init__.py
krxpy/calender/base.py
krxpy/calender/calender.py
krxpy/fnguide/__init__.py
krxpy/fnguide/base.py
krxpy/fnguide/table.py
krxpy/invest/__init__.py
krxpy/invest/base.py
krxpy/invest/shinhan.py
krxpy/kofia/__init__.py
krxpy/kofia/_header.py
krxpy/kofia/base.py
krxpy/kofia/data.py
krxpy/price/__init__.py
krxpy/price/base.py
krxpy/price/daum.py
krxpy/price/naver.py
krxpy/price/nxt.py
krxpy/py.typed
krxpy/pykrx/__init__.py
krxpy/pykrx/_krxio.py
krxpy/pykrx/_tools.py
krxpy/pykrx/_website.py
krxpy/pykrx/base.py
krxpy/pykrx/delist.py
krxpy/pykrx/foreign.py
krxpy/pykrx/investor.py
krxpy/pykrx/price.py
krxpy/pykrx/short.py
krxpy/pykrx/ticker.py
krxpy/stock/__init__.py
krxpy/stock/_headers.py
krxpy/stock/base.py
krxpy/stock/kind.py
krxpy/stock/naver.py
krxpy/stock/stock_api.py
krxpy/tools/__init__.py
krxpy/tools/base.py
krxpy/tools/dataframe.py
krxpy/tools/market.py
krxpy/trader/__init__.py
krxpy/trader/base.py
krxpy/trader/index.py
krxpy-0.0.11.dist-info/WHEEL
krxpy-0.0.11.dist-info/METADATA
krxpy-0.0.11.dist-info/RECORD
