Metadata-Version: 2.3
Name: krxpy
Version: 0.0.11
Summary: KRX Data Crawling ...
Author: Yong Beom, Kim
Author-email: Yong Beom, Kim <saltman21@naver.com>
Requires-Dist: pytip
Requires-Dist: pandas
Requires-Dist: lxml
Requires-Dist: tqdm
Requires-Dist: requests
Requires-Python: >=3.10
